{"language":"en","textAngle":0.0,"orientation":"Up","regions":[{"boundingBox":"137,130,624,315","lines":[{"boundingBox":"351,130,115,16","words":[{"boundingBox":"351,130,22,16","text":"(U)"},{"boundingBox":"380,130,86,12","text":"APPROVAL"}]},{"boundingBox":"160,168,475,17","words":[{"boundingBox":"160,170,21,15","text":"(U)"},{"boundingBox":"184,169,17,15","text":"(i"},{"boundingBox":"208,169,6,12","text":"I"},{"boundingBox":"218,169,27,12","text":"find"},{"boundingBox":"248,169,27,12","text":"that"},{"boundingBox":"278,169,25,12","text":"this"},{"boundingBox":"307,169,74,16","text":"application"},{"boundingBox":"385,169,65,16","text":"regarding"},{"boundingBox":"454,169,43,12","text":"Carter"},{"boundingBox":"500,169,19,12","text":"W."},{"boundingBox":"522,169,32,16","text":"Page"},{"boundingBox":"558,168,52,13","text":"satisfies"},{"boundingBox":"614,168,21,13","text":"the"}]},{"boundingBox":"138,209,465,17","words":[{"boundingBox":"138,210,47,12","text":"criteria"},{"boundingBox":"189,210,25,12","text":"and"},{"boundingBox":"218,210,88,16","text":"requirements"},{"boundingBox":"310,210,20,12","text":"for"},{"boundingBox":"333,210,31,12","text":"such"},{"boundingBox":"368,210,81,16","text":"applications"},{"boundingBox":"453,211,18,11","text":"set"},{"boundingBox":"475,209,33,13","text":"forth"},{"boundingBox":"511,210,13,12","text":"in"},{"boundingBox":"528,210,20,12","text":"the"},{"boundingBox":"552,210,51,16","text":"Foreign"}]},{"boundingBox":"137,250,527,17","words":[{"boundingBox":"137,250,78,17","text":"Intelligence"},{"boundingBox":"219,250,82,13","text":"Surveillance"},{"boundingBox":"304,251,24,12","text":"Act"},{"boundingBox":"331,250,14,13","text":"Of"},{"boundingBox":"348,251,33,14","text":"1978,"},{"boundingBox":"386,254,13,9","text":"as"},{"boundingBox":"403,250,66,14","text":"amended,"},{"boundingBox":"473,250,25,12","text":"and"},{"boundingBox":"502,250,45,16","text":"hereby"},{"boundingBox":"551,254,55,13","text":"approve"},{"boundingBox":"609,251,16,11","text":"its"},{"boundingBox":"629,250,35,16","text":"filing"}]},{"boundingBox":"137,292,105,12","words":[{"boundingBox":"137,292,32,12","text":"with"},{"boundingBox":"172,292,25,12","text":"this"},{"boundingBox":"200,292,42,12","text":"Court."}]},{"boundingBox":"698,377,26,12","words":[{"boundingBox":"698,377,26,12","text":"bi-l"}]},{"boundingBox":"698,395,26,12","words":[{"boundingBox":"698,395,26,12","text":"b3-l"}]},{"boundingBox":"698,413,36,12","words":[{"boundingBox":"698,413,36,12","text":"b7A-1"}]},{"boundingBox":"698,432,63,13","words":[{"boundingBox":"698,432,39,13","text":"b7E-l,"},{"boundingBox":"740,433,10,12","text":"2,"},{"boundingBox":"754,432,7,12","text":"6"}]}]}]}
