{"faces":[],"landmarks":[],"logos":[],"labels":[],"text":{"text":"(\nClandestine Intelligence Activities Of The Russian Federation\nb1-1\nb3-1\nb7A-1\nb7E-1,2\n2\nbl-1\nb3-1\nb7A-1\nb7E-1,2\n","locale":"en","bounds":[{"x":135,"y":119},{"x":771,"y":119},{"x":771,"y":836},{"x":135,"y":836}],"words":[{"text":"(","bounds":[{"x":135,"y":119},{"x":139,"y":119},{"x":139,"y":134},{"x":135,"y":134}]},{"text":"Clandestine","bounds":[{"x":160,"y":119},{"x":243,"y":119},{"x":243,"y":134},{"x":160,"y":134}]},{"text":"Intelligence","bounds":[{"x":250,"y":119},{"x":328,"y":119},{"x":328,"y":134},{"x":250,"y":134}]},{"text":"Activities","bounds":[{"x":335,"y":119},{"x":398,"y":119},{"x":398,"y":134},{"x":335,"y":134}]},{"text":"Of","bounds":[{"x":405,"y":119},{"x":421,"y":119},{"x":421,"y":134},{"x":405,"y":134}]},{"text":"The","bounds":[{"x":424,"y":119},{"x":452,"y":119},{"x":452,"y":134},{"x":424,"y":134}]},{"text":"Russian","bounds":[{"x":456,"y":119},{"x":508,"y":119},{"x":508,"y":134},{"x":456,"y":134}]},{"text":"Federation","bounds":[{"x":515,"y":119},{"x":587,"y":119},{"x":587,"y":134},{"x":515,"y":134}]},{"text":"b1-1","bounds":[{"x":721,"y":288},{"x":747,"y":289},{"x":746,"y":300},{"x":721,"y":299}]},{"text":"b3-1","bounds":[{"x":722,"y":305},{"x":746,"y":307},{"x":745,"y":319},{"x":721,"y":317}]},{"text":"b7A-1","bounds":[{"x":722,"y":324},{"x":757,"y":325},{"x":757,"y":336},{"x":722,"y":335}]},{"text":"b7E-1,2","bounds":[{"x":721,"y":343},{"x":771,"y":344},{"x":771,"y":355},{"x":721,"y":354}]},{"text":"2","bounds":[{"x":729,"y":327},{"x":732,"y":327},{"x":731,"y":355},{"x":728,"y":355}]},{"text":"bl-1","bounds":[{"x":717,"y":769},{"x":742,"y":771},{"x":741,"y":783},{"x":716,"y":781}]},{"text":"b3-1","bounds":[{"x":717,"y":788},{"x":742,"y":789},{"x":741,"y":800},{"x":717,"y":799}]},{"text":"b7A-1","bounds":[{"x":717,"y":806},{"x":753,"y":806},{"x":753,"y":817},{"x":717,"y":817}]},{"text":"b7E-1,2","bounds":[{"x":716,"y":824},{"x":766,"y":824},{"x":766,"y":836},{"x":716,"y":836}]}],"pages":[{"languages":[{"code":"en","confidence":0.0}],"break_type":null,"prefix_break":null,"width":815,"height":1055,"blocks":[{"languages":[{"code":"en","confidence":0.0}],"break_type":null,"prefix_break":null,"bounds":[{"x":135,"y":119},{"x":139,"y":119},{"x":139,"y":134},{"x":135,"y":134}],"paragraphs":[{"languages":[{"code":"en","confidence":0.0}],"break_type":null,"prefix_break":null,"bounds":[{"x":135,"y":119},{"x":139,"y":119},{"x":139,"y":134},{"x":135,"y":134}],"words":[{"languages":[{"code":"en","confidence":0.0}],"break_type":null,"prefix_break":null,"bounds":[{"x":135,"y":119},{"x":139,"y":119},{"x":139,"y":134},{"x":135,"y":134}],"symbols":[{"languages":[{"code":"en","confidence":0.0}],"break_type":"EOL_SURE_SPACE","prefix_break":false,"bounds":[{"x":135,"y":119},{"x":139,"y":119},{"x":139,"y":134},{"x":135,"y":134}],"text":"("}]}]}],"block_type":"TEXT"},{"languages":[{"code":"en","confidence":0.0}],"break_type":null,"prefix_break":null,"bounds":[{"x":160,"y":119},{"x":587,"y":119},{"x":587,"y":134},{"x":160,"y":134}],"paragraphs":[{"languages":[{"code":"en","confidence":0.0}],"break_type":null,"prefix_break":null,"bounds":[{"x":160,"y":119},{"x":587,"y":119},{"x":587,"y":134},{"x":160,"y":134}],"words":[{"languages":[{"code":"gl","confidence":0.0}],"break_type":null,"prefix_break":null,"bounds":[{"x":160,"y":119},{"x":243,"y":119},{"x":243,"y":134},{"x":160,"y":134}],"symbols":[{"languages":[{"code":"en","confidence":0.0}],"break_type":null,"prefix_break":null,"bounds":[{"x":160,"y":119},{"x":170,"y":119},{"x":170,"y":134},{"x":160,"y":134}],"text":"C"},{"languages":[{"code":"en","confidence":0.0}],"break_type":null,"prefix_break":null,"bounds":[{"x":171,"y":119},{"x":176,"y":119},{"x":176,"y":134},{"x":171,"y":134}],"text":"l"},{"languages":[{"code":"en","confidence":0.0}],"break_type":null,"prefix_break":null,"bounds":[{"x":177,"y":119},{"x":184,"y":119},{"x":184,"y":134},{"x":177,"y":134}],"text":"a"},{"languages":[{"code":"en","confidence":0.0}],"break_type":null,"prefix_break":null,"bounds":[{"x":185,"y":119},{"x":192,"y":119},{"x":192,"y":134},{"x":185,"y":134}],"text":"n"},{"languages":[{"code":"en","confidence":0.0}],"break_type":null,"prefix_break":null,"bounds":[{"x":193,"y":119},{"x":201,"y":119},{"x":201,"y":134},{"x":193,"y":134}],"text":"d"},{"languages":[{"code":"en","confidence":0.0}],"break_type":null,"prefix_break":null,"bounds":[{"x":202,"y":119},{"x":209,"y":119},{"x":209,"y":134},{"x":202,"y":134}],"text":"e"},{"languages":[{"code":"en","confidence":0.0}],"break_type":null,"prefix_break":null,"bounds":[{"x":210,"y":119},{"x":215,"y":119},{"x":215,"y":134},{"x":210,"y":134}],"text":"s"},{"languages":[{"code":"en","confidence":0.0}],"break_type":null,"prefix_break":null,"bounds":[{"x":216,"y":119},{"x":221,"y":119},{"x":221,"y":134},{"x":216,"y":134}],"text":"t"},{"languages":[{"code":"en","confidence":0.0}],"break_type":null,"prefix_break":null,"bounds":[{"x":222,"y":119},{"x":226,"y":119},{"x":226,"y":134},{"x":222,"y":134}],"text":"i"},{"languages":[{"code":"en","confidence":0.0}],"break_type":null,"prefix_break":null,"bounds":[{"x":227,"y":119},{"x":235,"y":119},{"x":235,"y":134},{"x":227,"y":134}],"text":"n"},{"languages":[{"code":"en","confidence":0.0}],"break_type":"SPACE","prefix_break":false,"bounds":[{"x":236,"y":119},{"x":243,"y":119},{"x":243,"y":134},{"x":236,"y":134}],"text":"e"}]},{"languages":[{"code":"en","confidence":0.0}],"break_type":null,"prefix_break":null,"bounds":[{"x":250,"y":119},{"x":328,"y":119},{"x":328,"y":134},{"x":250,"y":134}],"symbols":[{"languages":[{"code":"en","confidence":0.0}],"break_type":null,"prefix_break":null,"bounds":[{"x":250,"y":119},{"x":252,"y":119},{"x":252,"y":134},{"x":250,"y":134}],"text":"I"},{"languages":[{"code":"en","confidence":0.0}],"break_type":null,"prefix_break":null,"bounds":[{"x":253,"y":119},{"x":260,"y":119},{"x":260,"y":134},{"x":253,"y":134}],"text":"n"},{"languages":[{"code":"en","confidence":0.0}],"break_type":null,"prefix_break":null,"bounds":[{"x":261,"y":119},{"x":269,"y":119},{"x":269,"y":134},{"x":261,"y":134}],"text":"t"},{"languages":[{"code":"en","confidence":0.0}],"break_type":null,"prefix_break":null,"bounds":[{"x":270,"y":119},{"x":274,"y":119},{"x":274,"y":134},{"x":270,"y":134}],"text":"e"},{"languages":[{"code":"en","confidence":0.0}],"break_type":null,"prefix_break":null,"bounds":[{"x":275,"y":119},{"x":277,"y":119},{"x":277,"y":134},{"x":275,"y":134}],"text":"l"},{"languages":[{"code":"en","confidence":0.0}],"break_type":null,"prefix_break":null,"bounds":[{"x":278,"y":119},{"x":286,"y":119},{"x":286,"y":134},{"x":278,"y":134}],"text":"l"},{"languages":[{"code":"en","confidence":0.0}],"break_type":null,"prefix_break":null,"bounds":[{"x":287,"y":119},{"x":288,"y":119},{"x":288,"y":134},{"x":287,"y":134}],"text":"i"},{"languages":[{"code":"en","confidence":0.0}],"break_type":null,"prefix_break":null,"bounds":[{"x":289,"y":119},{"x":297,"y":119},{"x":297,"y":134},{"x":289,"y":134}],"text":"g"},{"languages":[{"code":"en","confidence":0.0}],"break_type":null,"prefix_break":null,"bounds":[{"x":298,"y":119},{"x":305,"y":119},{"x":305,"y":134},{"x":298,"y":134}],"text":"e"},{"languages":[{"code":"en","confidence":0.0}],"break_type":null,"prefix_break":null,"bounds":[{"x":306,"y":119},{"x":314,"y":119},{"x":314,"y":134},{"x":306,"y":134}],"text":"n"},{"languages":[{"code":"en","confidence":0.0}],"break_type":null,"prefix_break":null,"bounds":[{"x":315,"y":119},{"x":322,"y":119},{"x":322,"y":134},{"x":315,"y":134}],"text":"c"},{"languages":[{"code":"en","confidence":0.0}],"break_type":"SPACE","prefix_break":false,"bounds":[{"x":323,"y":119},{"x":328,"y":119},{"x":328,"y":134},{"x":323,"y":134}],"text":"e"}]},{"languages":[{"code":"en","confidence":0.0}],"break_type":null,"prefix_break":null,"bounds":[{"x":335,"y":119},{"x":398,"y":119},{"x":398,"y":134},{"x":335,"y":134}],"symbols":[{"languages":[{"code":"en","confidence":0.0}],"break_type":null,"prefix_break":null,"bounds":[{"x":335,"y":119},{"x":342,"y":119},{"x":342,"y":134},{"x":335,"y":134}],"text":"A"},{"languages":[{"code":"en","confidence":0.0}],"break_type":null,"prefix_break":null,"bounds":[{"x":343,"y":119},{"x":350,"y":119},{"x":350,"y":134},{"x":343,"y":134}],"text":"c"},{"languages":[{"code":"en","confidence":0.0}],"break_type":null,"prefix_break":null,"bounds":[{"x":351,"y":119},{"x":356,"y":119},{"x":356,"y":134},{"x":351,"y":134}],"text":"t"},{"languages":[{"code":"en","confidence":0.0}],"break_type":null,"prefix_break":null,"bounds":[{"x":357,"y":119},{"x":362,"y":119},{"x":362,"y":134},{"x":357,"y":134}],"text":"i"},{"languages":[{"code":"en","confidence":0.0}],"break_type":null,"prefix_break":null,"bounds":[{"x":363,"y":119},{"x":370,"y":119},{"x":370,"y":134},{"x":363,"y":134}],"text":"v"},{"languages":[{"code":"en","confidence":0.0}],"break_type":null,"prefix_break":null,"bounds":[{"x":371,"y":119},{"x":373,"y":119},{"x":373,"y":134},{"x":371,"y":134}],"text":"i"},{"languages":[{"code":"en","confidence":0.0}],"break_type":null,"prefix_break":null,"bounds":[{"x":374,"y":119},{"x":378,"y":119},{"x":378,"y":134},{"x":374,"y":134}],"text":"t"},{"languages":[{"code":"en","confidence":0.0}],"break_type":null,"prefix_break":null,"bounds":[{"x":379,"y":119},{"x":384,"y":119},{"x":384,"y":134},{"x":379,"y":134}],"text":"i"},{"languages":[{"code":"en","confidence":0.0}],"break_type":null,"prefix_break":null,"bounds":[{"x":385,"y":119},{"x":393,"y":119},{"x":393,"y":134},{"x":385,"y":134}],"text":"e"},{"languages":[{"code":"en","confidence":0.0}],"break_type":"SPACE","prefix_break":false,"bounds":[{"x":394,"y":119},{"x":398,"y":119},{"x":398,"y":134},{"x":394,"y":134}],"text":"s"}]},{"languages":[{"code":"en","confidence":0.0}],"break_type":null,"prefix_break":null,"bounds":[{"x":405,"y":119},{"x":421,"y":119},{"x":421,"y":134},{"x":405,"y":134}],"symbols":[{"languages":[{"code":"en","confidence":0.0}],"break_type":null,"prefix_break":null,"bounds":[{"x":405,"y":119},{"x":412,"y":119},{"x":412,"y":134},{"x":405,"y":134}],"text":"O"},{"languages":[{"code":"en","confidence":0.0}],"break_type":"SPACE","prefix_break":false,"bounds":[{"x":413,"y":119},{"x":421,"y":119},{"x":421,"y":134},{"x":413,"y":134}],"text":"f"}]},{"languages":[{"code":"en","confidence":0.0}],"break_type":null,"prefix_break":null,"bounds":[{"x":424,"y":119},{"x":452,"y":119},{"x":452,"y":134},{"x":424,"y":134}],"symbols":[{"languages":[{"code":"en","confidence":0.0}],"break_type":null,"prefix_break":null,"bounds":[{"x":424,"y":119},{"x":435,"y":119},{"x":435,"y":134},{"x":424,"y":134}],"text":"T"},{"languages":[{"code":"en","confidence":0.0}],"break_type":null,"prefix_break":null,"bounds":[{"x":436,"y":119},{"x":443,"y":119},{"x":443,"y":134},{"x":436,"y":134}],"text":"h"},{"languages":[{"code":"en","confidence":0.0}],"break_type":"SPACE","prefix_break":false,"bounds":[{"x":444,"y":119},{"x":452,"y":119},{"x":452,"y":134},{"x":444,"y":134}],"text":"e"}]},{"languages":[{"code":"en","confidence":0.0}],"break_type":null,"prefix_break":null,"bounds":[{"x":456,"y":119},{"x":508,"y":119},{"x":508,"y":134},{"x":456,"y":134}],"symbols":[{"languages":[{"code":"en","confidence":0.0}],"break_type":null,"prefix_break":null,"bounds":[{"x":456,"y":119},{"x":463,"y":119},{"x":463,"y":134},{"x":456,"y":134}],"text":"R"},{"languages":[{"code":"en","confidence":0.0}],"break_type":null,"prefix_break":null,"bounds":[{"x":464,"y":119},{"x":474,"y":119},{"x":474,"y":134},{"x":464,"y":134}],"text":"u"},{"languages":[{"code":"en","confidence":0.0}],"break_type":null,"prefix_break":null,"bounds":[{"x":475,"y":119},{"x":480,"y":119},{"x":480,"y":134},{"x":475,"y":134}],"text":"s"},{"languages":[{"code":"en","confidence":0.0}],"break_type":null,"prefix_break":null,"bounds":[{"x":481,"y":119},{"x":489,"y":119},{"x":489,"y":134},{"x":481,"y":134}],"text":"s"},{"languages":[{"code":"en","confidence":0.0}],"break_type":null,"prefix_break":null,"bounds":[{"x":490,"y":119},{"x":494,"y":119},{"x":494,"y":134},{"x":490,"y":134}],"text":"i"},{"languages":[{"code":"en","confidence":0.0}],"break_type":null,"prefix_break":null,"bounds":[{"x":495,"y":119},{"x":500,"y":119},{"x":500,"y":134},{"x":495,"y":134}],"text":"a"},{"languages":[{"code":"en","confidence":0.0}],"break_type":"SPACE","prefix_break":false,"bounds":[{"x":501,"y":119},{"x":508,"y":119},{"x":508,"y":134},{"x":501,"y":134}],"text":"n"}]},{"languages":[{"code":"en","confidence":0.0}],"break_type":null,"prefix_break":null,"bounds":[{"x":515,"y":119},{"x":587,"y":119},{"x":587,"y":134},{"x":515,"y":134}],"symbols":[{"languages":[{"code":"en","confidence":0.0}],"break_type":null,"prefix_break":null,"bounds":[{"x":515,"y":119},{"x":522,"y":119},{"x":522,"y":134},{"x":515,"y":134}],"text":"F"},{"languages":[{"code":"en","confidence":0.0}],"break_type":null,"prefix_break":null,"bounds":[{"x":523,"y":119},{"x":528,"y":119},{"x":528,"y":134},{"x":523,"y":134}],"text":"e"},{"languages":[{"code":"en","confidence":0.0}],"break_type":null,"prefix_break":null,"bounds":[{"x":529,"y":119},{"x":536,"y":119},{"x":536,"y":134},{"x":529,"y":134}],"text":"d"},{"languages":[{"code":"en","confidence":0.0}],"break_type":null,"prefix_break":null,"bounds":[{"x":537,"y":119},{"x":545,"y":119},{"x":545,"y":134},{"x":537,"y":134}],"text":"e"},{"languages":[{"code":"en","confidence":0.0}],"break_type":null,"prefix_break":null,"bounds":[{"x":546,"y":119},{"x":553,"y":119},{"x":553,"y":134},{"x":546,"y":134}],"text":"r"},{"languages":[{"code":"en","confidence":0.0}],"break_type":null,"prefix_break":null,"bounds":[{"x":554,"y":119},{"x":559,"y":119},{"x":559,"y":134},{"x":554,"y":134}],"text":"a"},{"languages":[{"code":"en","confidence":0.0}],"break_type":null,"prefix_break":null,"bounds":[{"x":560,"y":119},{"x":565,"y":119},{"x":565,"y":134},{"x":560,"y":134}],"text":"t"},{"languages":[{"code":"en","confidence":0.0}],"break_type":null,"prefix_break":null,"bounds":[{"x":566,"y":119},{"x":570,"y":119},{"x":570,"y":134},{"x":566,"y":134}],"text":"i"},{"languages":[{"code":"en","confidence":0.0}],"break_type":null,"prefix_break":null,"bounds":[{"x":571,"y":119},{"x":579,"y":119},{"x":579,"y":134},{"x":571,"y":134}],"text":"o"},{"languages":[{"code":"en","confidence":0.0}],"break_type":"EOL_SURE_SPACE","prefix_break":false,"bounds":[{"x":580,"y":119},{"x":587,"y":119},{"x":587,"y":134},{"x":580,"y":134}],"text":"n"}]}]}],"block_type":"TEXT"},{"languages":[{"code":"en","confidence":0.0}],"break_type":null,"prefix_break":null,"bounds":[{"x":721,"y":288},{"x":771,"y":288},{"x":771,"y":355},{"x":721,"y":355}],"paragraphs":[{"languages":[{"code":"en","confidence":0.0}],"break_type":null,"prefix_break":null,"bounds":[{"x":721,"y":288},{"x":771,"y":288},{"x":771,"y":355},{"x":721,"y":355}],"words":[{"languages":[{"code":"en","confidence":0.0}],"break_type":null,"prefix_break":null,"bounds":[{"x":721,"y":288},{"x":747,"y":289},{"x":746,"y":300},{"x":721,"y":299}],"symbols":[{"languages":[{"code":"en","confidence":0.0}],"break_type":null,"prefix_break":null,"bounds":[{"x":721,"y":288},{"x":728,"y":288},{"x":728,"y":299},{"x":721,"y":299}],"text":"b"},{"languages":[{"code":"en","confidence":0.0}],"break_type":null,"prefix_break":null,"bounds":[{"x":730,"y":288},{"x":735,"y":288},{"x":735,"y":298},{"x":730,"y":298}],"text":"1"},{"languages":[{"code":"en","confidence":0.0}],"break_type":null,"prefix_break":null,"bounds":[{"x":736,"y":289},{"x":740,"y":289},{"x":740,"y":299},{"x":736,"y":299}],"text":"-"},{"languages":[{"code":"en","confidence":0.0}],"break_type":"EOL_SURE_SPACE","prefix_break":false,"bounds":[{"x":743,"y":289},{"x":747,"y":289},{"x":747,"y":299},{"x":743,"y":299}],"text":"1"}]},{"languages":[{"code":"en","confidence":0.0}],"break_type":null,"prefix_break":null,"bounds":[{"x":722,"y":305},{"x":746,"y":307},{"x":745,"y":319},{"x":721,"y":317}],"symbols":[{"languages":[{"code":"en","confidence":0.0}],"break_type":null,"prefix_break":null,"bounds":[{"x":722,"y":305},{"x":728,"y":306},{"x":727,"y":317},{"x":721,"y":317}],"text":"b"},{"languages":[{"code":"en","confidence":0.0}],"break_type":null,"prefix_break":null,"bounds":[{"x":729,"y":307},{"x":734,"y":307},{"x":733,"y":317},{"x":728,"y":317}],"text":"3"},{"languages":[{"code":"en","confidence":0.0}],"break_type":null,"prefix_break":null,"bounds":[{"x":736,"y":306},{"x":741,"y":306},{"x":740,"y":316},{"x":735,"y":316}],"text":"-"},{"languages":[{"code":"en","confidence":0.0}],"break_type":"EOL_SURE_SPACE","prefix_break":false,"bounds":[{"x":742,"y":307},{"x":746,"y":307},{"x":745,"y":317},{"x":741,"y":317}],"text":"1"}]},{"languages":[{"code":"en","confidence":0.0}],"break_type":null,"prefix_break":null,"bounds":[{"x":722,"y":324},{"x":757,"y":325},{"x":757,"y":336},{"x":722,"y":335}],"symbols":[{"languages":[{"code":"en","confidence":0.0}],"break_type":null,"prefix_break":null,"bounds":[{"x":722,"y":324},{"x":728,"y":324},{"x":728,"y":335},{"x":722,"y":335}],"text":"b"},{"languages":[{"code":"en","confidence":0.0}],"break_type":null,"prefix_break":null,"bounds":[{"x":729,"y":325},{"x":735,"y":325},{"x":735,"y":335},{"x":729,"y":335}],"text":"7"},{"languages":[{"code":"en","confidence":0.0}],"break_type":null,"prefix_break":null,"bounds":[{"x":736,"y":325},{"x":743,"y":325},{"x":743,"y":335},{"x":736,"y":335}],"text":"A"},{"languages":[{"code":"en","confidence":0.0}],"break_type":null,"prefix_break":null,"bounds":[{"x":744,"y":326},{"x":751,"y":326},{"x":751,"y":336},{"x":744,"y":336}],"text":"-"},{"languages":[{"code":"en","confidence":0.0}],"break_type":"EOL_SURE_SPACE","prefix_break":false,"bounds":[{"x":753,"y":325},{"x":757,"y":325},{"x":757,"y":335},{"x":753,"y":335}],"text":"1"}]},{"languages":[{"code":"en","confidence":0.0}],"break_type":null,"prefix_break":null,"bounds":[{"x":721,"y":343},{"x":771,"y":344},{"x":771,"y":355},{"x":721,"y":354}],"symbols":[{"languages":[{"code":"en","confidence":0.0}],"break_type":null,"prefix_break":null,"bounds":[{"x":721,"y":343},{"x":728,"y":343},{"x":728,"y":354},{"x":721,"y":354}],"text":"b"},{"languages":[{"code":"en","confidence":0.0}],"break_type":null,"prefix_break":null,"bounds":[{"x":728,"y":344},{"x":736,"y":344},{"x":736,"y":354},{"x":728,"y":354}],"text":"7"},{"languages":[{"code":"en","confidence":0.0}],"break_type":null,"prefix_break":null,"bounds":[{"x":737,"y":344},{"x":744,"y":344},{"x":744,"y":354},{"x":737,"y":354}],"text":"E"},{"languages":[{"code":"en","confidence":0.0}],"break_type":null,"prefix_break":null,"bounds":[{"x":746,"y":344},{"x":750,"y":344},{"x":750,"y":354},{"x":746,"y":354}],"text":"-"},{"languages":[{"code":"en","confidence":0.0}],"break_type":null,"prefix_break":null,"bounds":[{"x":751,"y":345},{"x":755,"y":345},{"x":755,"y":355},{"x":751,"y":355}],"text":"1"},{"languages":[{"code":"en","confidence":0.0}],"break_type":null,"prefix_break":null,"bounds":[{"x":758,"y":352},{"x":760,"y":352},{"x":760,"y":355},{"x":758,"y":355}],"text":","},{"languages":[{"code":"en","confidence":0.0}],"break_type":"EOL_SURE_SPACE","prefix_break":false,"bounds":[{"x":764,"y":344},{"x":771,"y":344},{"x":771,"y":354},{"x":764,"y":354}],"text":"2"}]}]}],"block_type":"TEXT"},{"languages":[{"code":"en","confidence":0.0}],"break_type":null,"prefix_break":null,"bounds":[{"x":728,"y":327},{"x":732,"y":327},{"x":732,"y":355},{"x":728,"y":355}],"paragraphs":[{"languages":[{"code":"en","confidence":0.0}],"break_type":null,"prefix_break":null,"bounds":[{"x":728,"y":327},{"x":732,"y":327},{"x":732,"y":355},{"x":728,"y":355}],"words":[{"languages":[{"code":"en","confidence":0.0}],"break_type":null,"prefix_break":null,"bounds":[{"x":729,"y":327},{"x":732,"y":327},{"x":731,"y":355},{"x":728,"y":355}],"symbols":[{"languages":[{"code":"en","confidence":0.0}],"break_type":"EOL_SURE_SPACE","prefix_break":false,"bounds":[{"x":729,"y":327},{"x":732,"y":327},{"x":731,"y":355},{"x":728,"y":355}],"text":"2"}]}]}],"block_type":"TEXT"},{"languages":[{"code":"en","confidence":0.0}],"break_type":null,"prefix_break":null,"bounds":[{"x":716,"y":769},{"x":766,"y":769},{"x":766,"y":836},{"x":716,"y":836}],"paragraphs":[{"languages":[{"code":"en","confidence":0.0}],"break_type":null,"prefix_break":null,"bounds":[{"x":716,"y":769},{"x":766,"y":769},{"x":766,"y":836},{"x":716,"y":836}],"words":[{"languages":[{"code":"en","confidence":0.0}],"break_type":null,"prefix_break":null,"bounds":[{"x":717,"y":769},{"x":742,"y":771},{"x":741,"y":783},{"x":716,"y":781}],"symbols":[{"languages":[{"code":"en","confidence":0.0}],"break_type":null,"prefix_break":null,"bounds":[{"x":717,"y":770},{"x":724,"y":771},{"x":723,"y":782},{"x":716,"y":781}],"text":"b"},{"languages":[{"code":"en","confidence":0.0}],"break_type":null,"prefix_break":null,"bounds":[{"x":726,"y":771},{"x":730,"y":771},{"x":729,"y":781},{"x":725,"y":781}],"text":"l"},{"languages":[{"code":"en","confidence":0.0}],"break_type":null,"prefix_break":null,"bounds":[{"x":731,"y":771},{"x":735,"y":771},{"x":734,"y":781},{"x":730,"y":781}],"text":"-"},{"languages":[{"code":"en","confidence":0.0}],"break_type":"EOL_SURE_SPACE","prefix_break":false,"bounds":[{"x":738,"y":771},{"x":742,"y":771},{"x":741,"y":781},{"x":737,"y":781}],"text":"1"}]},{"languages":[{"code":"en","confidence":0.0}],"break_type":null,"prefix_break":null,"bounds":[{"x":717,"y":788},{"x":742,"y":789},{"x":741,"y":800},{"x":717,"y":799}],"symbols":[{"languages":[{"code":"en","confidence":0.0}],"break_type":null,"prefix_break":null,"bounds":[{"x":717,"y":788},{"x":724,"y":788},{"x":724,"y":799},{"x":717,"y":799}],"text":"b"},{"languages":[{"code":"en","confidence":0.0}],"break_type":null,"prefix_break":null,"bounds":[{"x":724,"y":788},{"x":729,"y":788},{"x":729,"y":798},{"x":724,"y":798}],"text":"3"},{"languages":[{"code":"en","confidence":0.0}],"break_type":null,"prefix_break":null,"bounds":[{"x":730,"y":789},{"x":736,"y":789},{"x":736,"y":799},{"x":730,"y":799}],"text":"-"},{"languages":[{"code":"en","confidence":0.0}],"break_type":"EOL_SURE_SPACE","prefix_break":false,"bounds":[{"x":739,"y":789},{"x":742,"y":789},{"x":742,"y":799},{"x":739,"y":799}],"text":"1"}]},{"languages":[{"code":"en","confidence":0.0}],"break_type":null,"prefix_break":null,"bounds":[{"x":717,"y":806},{"x":753,"y":806},{"x":753,"y":817},{"x":717,"y":817}],"symbols":[{"languages":[{"code":"en","confidence":0.0}],"break_type":null,"prefix_break":null,"bounds":[{"x":717,"y":806},{"x":723,"y":806},{"x":723,"y":817},{"x":717,"y":817}],"text":"b"},{"languages":[{"code":"en","confidence":0.0}],"break_type":null,"prefix_break":null,"bounds":[{"x":724,"y":807},{"x":730,"y":807},{"x":730,"y":816},{"x":724,"y":816}],"text":"7"},{"languages":[{"code":"en","confidence":0.0}],"break_type":null,"prefix_break":null,"bounds":[{"x":731,"y":807},{"x":738,"y":807},{"x":738,"y":817},{"x":731,"y":817}],"text":"A"},{"languages":[{"code":"en","confidence":0.0}],"break_type":null,"prefix_break":null,"bounds":[{"x":739,"y":807},{"x":746,"y":807},{"x":746,"y":817},{"x":739,"y":817}],"text":"-"},{"languages":[{"code":"en","confidence":0.0}],"break_type":"EOL_SURE_SPACE","prefix_break":false,"bounds":[{"x":749,"y":807},{"x":753,"y":807},{"x":753,"y":817},{"x":749,"y":817}],"text":"1"}]},{"languages":[{"code":"en","confidence":0.0}],"break_type":null,"prefix_break":null,"bounds":[{"x":716,"y":824},{"x":766,"y":824},{"x":766,"y":836},{"x":716,"y":836}],"symbols":[{"languages":[{"code":"en","confidence":0.0}],"break_type":null,"prefix_break":null,"bounds":[{"x":716,"y":824},{"x":723,"y":824},{"x":723,"y":835},{"x":716,"y":835}],"text":"b"},{"languages":[{"code":"en","confidence":0.0}],"break_type":null,"prefix_break":null,"bounds":[{"x":724,"y":824},{"x":730,"y":824},{"x":730,"y":834},{"x":724,"y":834}],"text":"7"},{"languages":[{"code":"en","confidence":0.0}],"break_type":null,"prefix_break":null,"bounds":[{"x":731,"y":824},{"x":737,"y":824},{"x":737,"y":835},{"x":731,"y":835}],"text":"E"},{"languages":[{"code":"en","confidence":0.0}],"break_type":null,"prefix_break":null,"bounds":[{"x":738,"y":824},{"x":744,"y":824},{"x":744,"y":835},{"x":738,"y":835}],"text":"-"},{"languages":[{"code":"en","confidence":0.0}],"break_type":null,"prefix_break":null,"bounds":[{"x":746,"y":825},{"x":751,"y":825},{"x":751,"y":835},{"x":746,"y":835}],"text":"1"},{"languages":[{"code":"en","confidence":0.0}],"break_type":null,"prefix_break":null,"bounds":[{"x":752,"y":832},{"x":756,"y":832},{"x":756,"y":836},{"x":752,"y":836}],"text":","},{"languages":[{"code":"en","confidence":0.0}],"break_type":"EOL_SURE_SPACE","prefix_break":false,"bounds":[{"x":759,"y":825},{"x":766,"y":825},{"x":766,"y":835},{"x":759,"y":835}],"text":"2"}]}]}],"block_type":"TEXT"}]}]},"safe_search":{},"properties":{},"crop_hints":[],"web":{},"object_localizations":{}}
